LICENSE
MANIFEST.in
README
distribute_setup.py
setup.cfg
setup.py
docs/.DS_Store
docs/.gitignore
docs/Makefile
docs/conf.py
docs/index.rst
docs/messages.rst
docs/_build/doctrees/environment.pickle
docs/_build/doctrees/index.doctree
docs/_build/doctrees/messages.doctree
docs/_build/html/.buildinfo
docs/_build/html/genindex.html
docs/_build/html/index.html
docs/_build/html/messages.html
docs/_build/html/modindex.html
docs/_build/html/objects.inv
docs/_build/html/search.html
docs/_build/html/searchindex.js
docs/_build/html/_sources/index.txt
docs/_build/html/_sources/messages.txt
docs/_build/html/_static/basic.css
docs/_build/html/_static/default.css
docs/_build/html/_static/doctools.js
docs/_build/html/_static/file.png
docs/_build/html/_static/jquery.js
docs/_build/html/_static/minus.png
docs/_build/html/_static/plus.png
docs/_build/html/_static/pygments.css
docs/_build/html/_static/searchtools.js
maillib/__init__.py
maillib.egg-info/PKG-INFO
maillib.egg-info/SOURCES.txt
maillib.egg-info/dependency_links.txt
maillib.egg-info/requires.txt
maillib.egg-info/top_level.txt