Metadata-Version: 1.0
Name: maillib
Version: 0.1.3
Summary: A simplified interface to Python's email package.
Home-page: http://github.com/jkocherhans/maillib
Author: Joseph Kocherhans
Author-email: jkocherhans@gmail.com
License: BSD
Platform: UNKNOWN
Classifier: Development Status :: 3 - Alpha
Classifier: Intended Audience :: Developers
Classifier: License :: OSI Approved :: BSD License
Classifier: Operating System :: OS Independent
Classifier: Programming Language :: Python
Classifier: Topic :: Communications :: Email
